quic_migration_tester/__init__.py
quic_migration_tester/main.py
quic_migration_tester-0.1.0.dist-info/METADATA
quic_migration_tester-0.1.0.dist-info/WHEEL
quic_migration_tester-0.1.0.dist-info/entry_points.txt
quic_migration_tester-0.1.0.dist-info/licenses/LICENSE
quic_migration_tester-0.1.0.dist-info/RECORD
