Metadata-Version: 2.4
Name: quic-migration-tester
Version: 0.1.0
Summary: A Python tool for testing HTTP/3 websites' support for QUIC connection migration by analyzing connection parameters and simulating network changes.
Project-URL: Homepage, https://github.com/stackia/quic-migration-tester
Project-URL: Repository, https://github.com/stackia/quic-migration-tester
Project-URL: Issues, https://github.com/stackia/quic-migration-tester/issues
Project-URL: Documentation, https://github.com/stackia/quic-migration-tester#readme
Author-email: Stackie Jia <jsq2627@gmail.com>
Maintainer-email: Stackie Jia <jsq2627@gmail.com>
License-Expression: MIT
License-File: LICENSE
Keywords: connection-migration,http3,network-testing,protocol-testing,quic,rfc9000
Classifier: Development Status :: 4 - Beta
Classifier: Environment :: Console
Classifier: Intended Audience :: Developers
Classifier: Intended Audience :: System Administrators
Classifier: License :: OSI Approved :: MIT License
Classifier: Operating System :: OS Independent
Classifier: Programming Language :: Python :: 3
Classifier: Programming Language :: Python :: 3.13
Classifier: Topic :: Internet :: WWW/HTTP
Classifier: Topic :: Software Development :: Testing
Classifier: Topic :: System :: Networking
Classifier: Topic :: Utilities
Requires-Python: >=3.13
Requires-Dist: aioquic>=1.2.0
